{
  "text": "её\nВ\nвиде\nдe-\nСократите\nдробь\nи\nобыкновенную\nпредставьте\nсятичной\n9:8\nа\nђо\n5оз\nо\nо\nоо\n2\nб\nдо\nB\nзђ\nЗаполните\nобыкновенную\nI.\nропуски\nесли\nразло\nдробь\nнельзя\nпредставить\nвиде\nдесятичной\nВ\nВ\nеё\nбы\nмножители\nесть\nхотя\nжении\nзнаменателя\nна\nпростые\nчисло\nодн\nотличное\nт\nчисел\n8.\nBыясните\nможно\nдробь\nпредставить\nданную\nвиде\nдеся\nли\nтичной\nзапишите\nеё\nесли\nBозможно\nB\nвиде\nоце\nдесятич\nHOй!\nа\nб\nэту\nдробь\nпредста\n2\n2.2.\nдроби\nвить\nвиде\nдесятичной\n2?\nђ\n4Т\nмножение\nHа\nдесятичную\nдробь\nНайдите\nпроизведение\nа2,т\nO,l-\n2,7:10\nб\n6,2\nO,O\n6,2\n?\nоо",
  "ocr_results": [
    {
      "bbox": [
        [
          1861.0,
          230.0
        ],
        [
          1932.0,
          230.0
        ],
        [
          1932.0,
          288.0
        ],
        [
          1861.0,
          288.0
        ]
      ],
      "text": "её",
      "confidence": 0.9265720844268799
    },
    {
      "bbox": [
        [
          1952.0,
          240.0
        ],
        [
          1985.0,
          240.0
        ],
        [
          1985.0,
          278.0
        ],
        [
          1952.0,
          278.0
        ]
      ],
      "text": "В",
      "confidence": 0.6314510703086853
    },
    {
      "bbox": [
        [
          2012.0,
          237.0
        ],
        [
          2161.0,
          237.0
        ],
        [
          2161.0,
          288.0
        ],
        [
          2012.0,
          288.0
        ]
      ],
      "text": "виде",
      "confidence": 0.9959288835525513
    },
    {
      "bbox": [
        [
          2181.0,
          237.0
        ],
        [
          2269.0,
          237.0
        ],
        [
          2269.0,
          288.0
        ],
        [
          2181.0,
          288.0
        ]
      ],
      "text": "дe-",
      "confidence": 0.6943526864051819
    },
    {
      "bbox": [
        [
          373.0,
          250.0
        ],
        [
          699.0,
          265.0
        ],
        [
          695.0,
          338.0
        ],
        [
          370.0,
          322.0
        ]
      ],
      "text": "Сократите",
      "confidence": 0.9988512396812439
    },
    {
      "bbox": [
        [
          1195.0,
          255.0
        ],
        [
          1372.0,
          243.0
        ],
        [
          1377.0,
          305.0
        ],
        [
          1200.0,
          317.0
        ]
      ],
      "text": "дробь",
      "confidence": 0.9981830716133118
    },
    {
      "bbox": [
        [
          1404.0,
          250.0
        ],
        [
          1449.0,
          260.0
        ],
        [
          1437.0,
          312.0
        ],
        [
          1393.0,
          302.0
        ]
      ],
      "text": "и",
      "confidence": 0.7446234822273254
    },
    {
      "bbox": [
        [
          725.0,
          264.0
        ],
        [
          1173.0,
          264.0
        ],
        [
          1173.0,
          313.0
        ],
        [
          725.0,
          313.0
        ]
      ],
      "text": "обыкновенную",
      "confidence": 0.9692173600196838
    },
    {
      "bbox": [
        [
          1462.0,
          255.0
        ],
        [
          1842.0,
          236.0
        ],
        [
          1845.0,
          294.0
        ],
        [
          1465.0,
          313.0
        ]
      ],
      "text": "представьте",
      "confidence": 0.9987034201622009
    },
    {
      "bbox": [
        [
          377.0,
          340.0
        ],
        [
          684.0,
          333.0
        ],
        [
          685.0,
          381.0
        ],
        [
          378.0,
          388.0
        ]
      ],
      "text": "сятичной",
      "confidence": 0.9848485589027405
    },
    {
      "bbox": [
        [
          674.0,
          433.0
        ],
        [
          779.0,
          433.0
        ],
        [
          779.0,
          481.0
        ],
        [
          674.0,
          481.0
        ]
      ],
      "text": "9:8",
      "confidence": 0.6591880917549133
    },
    {
      "bbox": [
        [
          384.0,
          472.0
        ],
        [
          435.0,
          483.0
        ],
        [
          425.0,
          528.0
        ],
        [
          374.0,
          516.0
        ]
      ],
      "text": "а",
      "confidence": 0.8520599603652954
    },
    {
      "bbox": [
        [
          472.0,
          501.0
        ],
        [
          556.0,
          501.0
        ],
        [
          556.0,
          543.0
        ],
        [
          472.0,
          543.0
        ]
      ],
      "text": "ђо",
      "confidence": 0.9347776174545288
    },
    {
      "bbox": [
        [
          647.0,
          498.0
        ],
        [
          806.0,
          498.0
        ],
        [
          806.0,
          546.0
        ],
        [
          647.0,
          546.0
        ]
      ],
      "text": "5оз",
      "confidence": 0.8822238445281982
    },
    {
      "bbox": [
        [
          893.0,
          501.0
        ],
        [
          951.0,
          501.0
        ],
        [
          951.0,
          543.0
        ],
        [
          893.0,
          543.0
        ]
      ],
      "text": "о",
      "confidence": 0.999112069606781
    },
    {
      "bbox": [
        [
          1045.0,
          498.0
        ],
        [
          1109.0,
          498.0
        ],
        [
          1109.0,
          539.0
        ],
        [
          1045.0,
          539.0
        ]
      ],
      "text": "о",
      "confidence": 0.9999309778213501
    },
    {
      "bbox": [
        [
          1271.0,
          498.0
        ],
        [
          1352.0,
          498.0
        ],
        [
          1352.0,
          536.0
        ],
        [
          1271.0,
          536.0
        ]
      ],
      "text": "оо",
      "confidence": 0.9316493272781372
    },
    {
      "bbox": [
        [
          479.0,
          609.0
        ],
        [
          537.0,
          598.0
        ],
        [
          545.0,
          644.0
        ],
        [
          488.0,
          655.0
        ]
      ],
      "text": "2",
      "confidence": 0.6987149119377136
    },
    {
      "bbox": [
        [
          381.0,
          632.0
        ],
        [
          438.0,
          632.0
        ],
        [
          438.0,
          697.0
        ],
        [
          381.0,
          697.0
        ]
      ],
      "text": "б",
      "confidence": 0.9973799586296082
    },
    {
      "bbox": [
        [
          472.0,
          658.0
        ],
        [
          565.0,
          668.0
        ],
        [
          559.0,
          719.0
        ],
        [
          467.0,
          709.0
        ]
      ],
      "text": "до",
      "confidence": 0.6456550359725952
    },
    {
      "bbox": [
        [
          398.0,
          800.0
        ],
        [
          438.0,
          800.0
        ],
        [
          438.0,
          855.0
        ],
        [
          398.0,
          855.0
        ]
      ],
      "text": "B",
      "confidence": 0.8139060139656067
    },
    {
      "bbox": [
        [
          721.0,
          838.0
        ],
        [
          779.0,
          838.0
        ],
        [
          779.0,
          879.0
        ],
        [
          721.0,
          879.0
        ]
      ],
      "text": "зђ",
      "confidence": 0.7255945205688477
    },
    {
      "bbox": [
        [
          385.0,
          971.0
        ],
        [
          715.0,
          979.0
        ],
        [
          714.0,
          1038.0
        ],
        [
          384.0,
          1030.0
        ]
      ],
      "text": "Заполните",
      "confidence": 0.9951158165931702
    },
    {
      "bbox": [
        [
          1807.0,
          968.0
        ],
        [
          2272.0,
          968.0
        ],
        [
          2272.0,
          1017.0
        ],
        [
          1807.0,
          1017.0
        ]
      ],
      "text": "обыкновенную",
      "confidence": 0.9837946891784668
    },
    {
      "bbox": [
        [
          290.0,
          979.0
        ],
        [
          337.0,
          979.0
        ],
        [
          337.0,
          1023.0
        ],
        [
          290.0,
          1023.0
        ]
      ],
      "text": "I.",
      "confidence": 0.8375755548477173
    },
    {
      "bbox": [
        [
          758.0,
          989.0
        ],
        [
          1062.0,
          989.0
        ],
        [
          1062.0,
          1037.0
        ],
        [
          758.0,
          1037.0
        ]
      ],
      "text": "ропуски",
      "confidence": 0.9879499673843384
    },
    {
      "bbox": [
        [
          1843.0,
          1045.0
        ],
        [
          1990.0,
          1036.0
        ],
        [
          1993.0,
          1088.0
        ],
        [
          1846.0,
          1096.0
        ]
      ],
      "text": "если",
      "confidence": 0.9991222023963928
    },
    {
      "bbox": [
        [
          2076.0,
          1037.0
        ],
        [
          2272.0,
          1037.0
        ],
        [
          2272.0,
          1096.0
        ],
        [
          2076.0,
          1096.0
        ]
      ],
      "text": "разло",
      "confidence": 0.9150363802909851
    },
    {
      "bbox": [
        [
          383.0,
          1056.0
        ],
        [
          560.0,
          1043.0
        ],
        [
          564.0,
          1101.0
        ],
        [
          387.0,
          1114.0
        ]
      ],
      "text": "дробь",
      "confidence": 0.9965773820877075
    },
    {
      "bbox": [
        [
          587.0,
          1054.0
        ],
        [
          792.0,
          1054.0
        ],
        [
          792.0,
          1102.0
        ],
        [
          587.0,
          1102.0
        ]
      ],
      "text": "нельзя",
      "confidence": 0.9803629517555237
    },
    {
      "bbox": [
        [
          819.0,
          1058.0
        ],
        [
          1193.0,
          1051.0
        ],
        [
          1194.0,
          1099.0
        ],
        [
          820.0,
          1106.0
        ]
      ],
      "text": "представить",
      "confidence": 0.9986979961395264
    },
    {
      "bbox": [
        [
          1274.0,
          1054.0
        ],
        [
          1412.0,
          1054.0
        ],
        [
          1412.0,
          1102.0
        ],
        [
          1274.0,
          1102.0
        ]
      ],
      "text": "виде",
      "confidence": 0.9943551421165466
    },
    {
      "bbox": [
        [
          1428.0,
          1052.0
        ],
        [
          1812.0,
          1033.0
        ],
        [
          1814.0,
          1091.0
        ],
        [
          1431.0,
          1110.0
        ]
      ],
      "text": "десятичной",
      "confidence": 0.998921275138855
    },
    {
      "bbox": [
        [
          2009.0,
          1049.0
        ],
        [
          2053.0,
          1037.0
        ],
        [
          2066.0,
          1082.0
        ],
        [
          2022.0,
          1095.0
        ]
      ],
      "text": "В",
      "confidence": 0.5726161003112793
    },
    {
      "bbox": [
        [
          1220.0,
          1061.0
        ],
        [
          1251.0,
          1061.0
        ],
        [
          1251.0,
          1099.0
        ],
        [
          1220.0,
          1099.0
        ]
      ],
      "text": "В",
      "confidence": 0.6110032796859741
    },
    {
      "bbox": [
        [
          616.0,
          1109.0
        ],
        [
          686.0,
          1118.0
        ],
        [
          679.0,
          1176.0
        ],
        [
          608.0,
          1167.0
        ]
      ],
      "text": "её",
      "confidence": 0.9592108726501465
    },
    {
      "bbox": [
        [
          2191.0,
          1102.0
        ],
        [
          2279.0,
          1102.0
        ],
        [
          2279.0,
          1157.0
        ],
        [
          2191.0,
          1157.0
        ]
      ],
      "text": "бы",
      "confidence": 0.9788436889648438
    },
    {
      "bbox": [
        [
          1486.0,
          1120.0
        ],
        [
          1844.0,
          1116.0
        ],
        [
          1844.0,
          1164.0
        ],
        [
          1487.0,
          1168.0
        ]
      ],
      "text": "множители",
      "confidence": 0.9964593052864075
    },
    {
      "bbox": [
        [
          1871.0,
          1120.0
        ],
        [
          1999.0,
          1120.0
        ],
        [
          1999.0,
          1157.0
        ],
        [
          1871.0,
          1157.0
        ]
      ],
      "text": "есть",
      "confidence": 0.9873579740524292
    },
    {
      "bbox": [
        [
          2018.0,
          1114.0
        ],
        [
          2166.0,
          1105.0
        ],
        [
          2168.0,
          1157.0
        ],
        [
          2021.0,
          1165.0
        ]
      ],
      "text": "хотя",
      "confidence": 0.949846625328064
    },
    {
      "bbox": [
        [
          394.0,
          1130.0
        ],
        [
          587.0,
          1130.0
        ],
        [
          587.0,
          1168.0
        ],
        [
          394.0,
          1168.0
        ]
      ],
      "text": "жении",
      "confidence": 0.9923427700996399
    },
    {
      "bbox": [
        [
          705.0,
          1126.0
        ],
        [
          1089.0,
          1126.0
        ],
        [
          1089.0,
          1171.0
        ],
        [
          705.0,
          1171.0
        ]
      ],
      "text": "знаменателя",
      "confidence": 0.9375410079956055
    },
    {
      "bbox": [
        [
          1116.0,
          1126.0
        ],
        [
          1187.0,
          1126.0
        ],
        [
          1187.0,
          1175.0
        ],
        [
          1116.0,
          1175.0
        ]
      ],
      "text": "на",
      "confidence": 0.8423867225646973
    },
    {
      "bbox": [
        [
          1210.0,
          1126.0
        ],
        [
          1466.0,
          1126.0
        ],
        [
          1466.0,
          1175.0
        ],
        [
          1210.0,
          1175.0
        ]
      ],
      "text": "простые",
      "confidence": 0.9907613396644592
    },
    {
      "bbox": [
        [
          554.0,
          1225.0
        ],
        [
          742.0,
          1233.0
        ],
        [
          740.0,
          1282.0
        ],
        [
          552.0,
          1274.0
        ]
      ],
      "text": "число",
      "confidence": 0.9971030354499817
    },
    {
      "bbox": [
        [
          394.0,
          1236.0
        ],
        [
          529.0,
          1236.0
        ],
        [
          529.0,
          1274.0
        ],
        [
          394.0,
          1274.0
        ]
      ],
      "text": "одн",
      "confidence": 0.9436376094818115
    },
    {
      "bbox": [
        [
          775.0,
          1230.0
        ],
        [
          1048.0,
          1230.0
        ],
        [
          1048.0,
          1274.0
        ],
        [
          775.0,
          1274.0
        ]
      ],
      "text": "отличное",
      "confidence": 0.9900752305984497
    },
    {
      "bbox": [
        [
          1075.0,
          1230.0
        ],
        [
          1139.0,
          1230.0
        ],
        [
          1139.0,
          1274.0
        ],
        [
          1075.0,
          1274.0
        ]
      ],
      "text": "т",
      "confidence": 0.9881029725074768
    },
    {
      "bbox": [
        [
          1163.0,
          1233.0
        ],
        [
          1328.0,
          1233.0
        ],
        [
          1328.0,
          1271.0
        ],
        [
          1163.0,
          1271.0
        ]
      ],
      "text": "чисел",
      "confidence": 0.9936202168464661
    },
    {
      "bbox": [
        [
          287.0,
          1374.0
        ],
        [
          344.0,
          1374.0
        ],
        [
          344.0,
          1436.0
        ],
        [
          287.0,
          1436.0
        ]
      ],
      "text": "8.",
      "confidence": 0.9469181895256042
    },
    {
      "bbox": [
        [
          392.0,
          1373.0
        ],
        [
          715.0,
          1385.0
        ],
        [
          713.0,
          1447.0
        ],
        [
          390.0,
          1435.0
        ]
      ],
      "text": "Bыясните",
      "confidence": 0.996037483215332
    },
    {
      "bbox": [
        [
          733.0,
          1380.0
        ],
        [
          948.0,
          1388.0
        ],
        [
          946.0,
          1447.0
        ],
        [
          731.0,
          1438.0
        ]
      ],
      "text": "можно",
      "confidence": 0.9882597923278809
    },
    {
      "bbox": [
        [
          1296.0,
          1386.0
        ],
        [
          1476.0,
          1369.0
        ],
        [
          1482.0,
          1430.0
        ],
        [
          1302.0,
          1447.0
        ]
      ],
      "text": "дробь",
      "confidence": 0.9979804754257202
    },
    {
      "bbox": [
        [
          1490.0,
          1381.0
        ],
        [
          1884.0,
          1377.0
        ],
        [
          1885.0,
          1435.0
        ],
        [
          1490.0,
          1439.0
        ]
      ],
      "text": "представить",
      "confidence": 0.9934898018836975
    },
    {
      "bbox": [
        [
          1055.0,
          1391.0
        ],
        [
          1291.0,
          1391.0
        ],
        [
          1291.0,
          1439.0
        ],
        [
          1055.0,
          1439.0
        ]
      ],
      "text": "данную",
      "confidence": 0.9976784586906433
    },
    {
      "bbox": [
        [
          1955.0,
          1384.0
        ],
        [
          2100.0,
          1384.0
        ],
        [
          2100.0,
          1436.0
        ],
        [
          1955.0,
          1436.0
        ]
      ],
      "text": "виде",
      "confidence": 0.964726448059082
    },
    {
      "bbox": [
        [
          2117.0,
          1384.0
        ],
        [
          2272.0,
          1384.0
        ],
        [
          2272.0,
          1436.0
        ],
        [
          2117.0,
          1436.0
        ]
      ],
      "text": "деся",
      "confidence": 0.8913778066635132
    },
    {
      "bbox": [
        [
          957.0,
          1394.0
        ],
        [
          1038.0,
          1394.0
        ],
        [
          1038.0,
          1436.0
        ],
        [
          957.0,
          1436.0
        ]
      ],
      "text": "ли",
      "confidence": 0.7800822257995605
    },
    {
      "bbox": [
        [
          394.0,
          1453.0
        ],
        [
          634.0,
          1453.0
        ],
        [
          634.0,
          1511.0
        ],
        [
          394.0,
          1511.0
        ]
      ],
      "text": "тичной",
      "confidence": 0.9716050624847412
    },
    {
      "bbox": [
        [
          1362.0,
          1456.0
        ],
        [
          1665.0,
          1456.0
        ],
        [
          1665.0,
          1504.0
        ],
        [
          1362.0,
          1504.0
        ]
      ],
      "text": "запишите",
      "confidence": 0.9997066259384155
    },
    {
      "bbox": [
        [
          1685.0,
          1449.0
        ],
        [
          1756.0,
          1449.0
        ],
        [
          1756.0,
          1504.0
        ],
        [
          1685.0,
          1504.0
        ]
      ],
      "text": "её",
      "confidence": 0.992918848991394
    },
    {
      "bbox": [
        [
          664.0,
          1460.0
        ],
        [
          802.0,
          1460.0
        ],
        [
          802.0,
          1508.0
        ],
        [
          664.0,
          1508.0
        ]
      ],
      "text": "если",
      "confidence": 0.9888008832931519
    },
    {
      "bbox": [
        [
          944.0,
          1460.0
        ],
        [
          1244.0,
          1460.0
        ],
        [
          1244.0,
          1504.0
        ],
        [
          944.0,
          1504.0
        ]
      ],
      "text": "Bозможно",
      "confidence": 0.846134603023529
    },
    {
      "bbox": [
        [
          1770.0,
          1456.0
        ],
        [
          1814.0,
          1456.0
        ],
        [
          1814.0,
          1501.0
        ],
        [
          1770.0,
          1501.0
        ]
      ],
      "text": "B",
      "confidence": 0.5873636603355408
    },
    {
      "bbox": [
        [
          1832.0,
          1452.0
        ],
        [
          1983.0,
          1460.0
        ],
        [
          1980.0,
          1512.0
        ],
        [
          1830.0,
          1503.0
        ]
      ],
      "text": "виде",
      "confidence": 0.9951633214950562
    },
    {
      "bbox": [
        [
          826.0,
          1463.0
        ],
        [
          920.0,
          1463.0
        ],
        [
          920.0,
          1508.0
        ],
        [
          826.0,
          1508.0
        ]
      ],
      "text": "оце",
      "confidence": 0.5731707215309143
    },
    {
      "bbox": [
        [
          2002.0,
          1460.0
        ],
        [
          2268.0,
          1452.0
        ],
        [
          2269.0,
          1500.0
        ],
        [
          2003.0,
          1508.0
        ]
      ],
      "text": "десятич",
      "confidence": 0.998906672000885
    },
    {
      "bbox": [
        [
          388.0,
          1518.0
        ],
        [
          529.0,
          1518.0
        ],
        [
          529.0,
          1580.0
        ],
        [
          388.0,
          1580.0
        ]
      ],
      "text": "HOй!",
      "confidence": 0.8052679300308228
    },
    {
      "bbox": [
        [
          405.0,
          1662.0
        ],
        [
          452.0,
          1662.0
        ],
        [
          452.0,
          1710.0
        ],
        [
          405.0,
          1710.0
        ]
      ],
      "text": "а",
      "confidence": 0.9469130635261536
    },
    {
      "bbox": [
        [
          398.0,
          1844.0
        ],
        [
          455.0,
          1844.0
        ],
        [
          455.0,
          1910.0
        ],
        [
          398.0,
          1910.0
        ]
      ],
      "text": "б",
      "confidence": 0.8910256028175354
    },
    {
      "bbox": [
        [
          1038.0,
          1855.0
        ],
        [
          1143.0,
          1855.0
        ],
        [
          1143.0,
          1906.0
        ],
        [
          1038.0,
          1906.0
        ]
      ],
      "text": "эту",
      "confidence": 0.9531487822532654
    },
    {
      "bbox": [
        [
          1165.0,
          1849.0
        ],
        [
          1345.0,
          1836.0
        ],
        [
          1350.0,
          1898.0
        ],
        [
          1169.0,
          1911.0
        ]
      ],
      "text": "дробь",
      "confidence": 0.9975903630256653
    },
    {
      "bbox": [
        [
          2012.0,
          1865.0
        ],
        [
          2271.0,
          1858.0
        ],
        [
          2273.0,
          1916.0
        ],
        [
          2014.0,
          1924.0
        ]
      ],
      "text": "предста",
      "confidence": 0.9280188679695129
    },
    {
      "bbox": [
        [
          492.0,
          1879.0
        ],
        [
          560.0,
          1879.0
        ],
        [
          560.0,
          1940.0
        ],
        [
          492.0,
          1940.0
        ]
      ],
      "text": "2",
      "confidence": 0.534278929233551
    },
    {
      "bbox": [
        [
          639.0,
          1878.0
        ],
        [
          773.0,
          1886.0
        ],
        [
          770.0,
          1938.0
        ],
        [
          636.0,
          1929.0
        ]
      ],
      "text": "2.2.",
      "confidence": 0.8898406028747559
    },
    {
      "bbox": [
        [
          1146.0,
          1947.0
        ],
        [
          1345.0,
          1947.0
        ],
        [
          1345.0,
          2009.0
        ],
        [
          1146.0,
          2009.0
        ]
      ],
      "text": "дроби",
      "confidence": 0.9989979863166809
    },
    {
      "bbox": [
        [
          398.0,
          1961.0
        ],
        [
          536.0,
          1961.0
        ],
        [
          536.0,
          2009.0
        ],
        [
          398.0,
          2009.0
        ]
      ],
      "text": "вить",
      "confidence": 0.9968942403793335
    },
    {
      "bbox": [
        [
          610.0,
          1961.0
        ],
        [
          752.0,
          1961.0
        ],
        [
          752.0,
          2009.0
        ],
        [
          610.0,
          2009.0
        ]
      ],
      "text": "виде",
      "confidence": 0.9964675903320312
    },
    {
      "bbox": [
        [
          768.0,
          1958.0
        ],
        [
          1121.0,
          1943.0
        ],
        [
          1123.0,
          2002.0
        ],
        [
          770.0,
          2017.0
        ]
      ],
      "text": "десятичной",
      "confidence": 0.9992910623550415
    },
    {
      "bbox": [
        [
          489.0,
          2033.0
        ],
        [
          553.0,
          2033.0
        ],
        [
          553.0,
          2116.0
        ],
        [
          489.0,
          2116.0
        ]
      ],
      "text": "2?",
      "confidence": 0.7869620323181152
    },
    {
      "bbox": [
        [
          492.0,
          2098.0
        ],
        [
          546.0,
          2098.0
        ],
        [
          546.0,
          2146.0
        ],
        [
          492.0,
          2146.0
        ]
      ],
      "text": "ђ",
      "confidence": 0.9704778790473938
    },
    {
      "bbox": [
        [
          415.0,
          2459.0
        ],
        [
          539.0,
          2459.0
        ],
        [
          539.0,
          2545.0
        ],
        [
          415.0,
          2545.0
        ]
      ],
      "text": "4Т",
      "confidence": 0.5346797108650208
    },
    {
      "bbox": [
        [
          591.0,
          2462.0
        ],
        [
          1069.0,
          2470.0
        ],
        [
          1068.0,
          2542.0
        ],
        [
          590.0,
          2534.0
        ]
      ],
      "text": "множение",
      "confidence": 0.9705619215965271
    },
    {
      "bbox": [
        [
          1102.0,
          2476.0
        ],
        [
          1203.0,
          2476.0
        ],
        [
          1203.0,
          2545.0
        ],
        [
          1102.0,
          2545.0
        ]
      ],
      "text": "Hа",
      "confidence": 0.8777016401290894
    },
    {
      "bbox": [
        [
          1236.0,
          2472.0
        ],
        [
          1747.0,
          2491.0
        ],
        [
          1744.0,
          2573.0
        ],
        [
          1233.0,
          2554.0
        ]
      ],
      "text": "десятичную",
      "confidence": 0.9990063905715942
    },
    {
      "bbox": [
        [
          1776.0,
          2484.0
        ],
        [
          2044.0,
          2475.0
        ],
        [
          2047.0,
          2571.0
        ],
        [
          1779.0,
          2580.0
        ]
      ],
      "text": "дробь",
      "confidence": 0.9994208216667175
    },
    {
      "bbox": [
        [
          398.0,
          2655.0
        ],
        [
          667.0,
          2655.0
        ],
        [
          667.0,
          2713.0
        ],
        [
          398.0,
          2713.0
        ]
      ],
      "text": "Найдите",
      "confidence": 0.9500051736831665
    },
    {
      "bbox": [
        [
          681.0,
          2665.0
        ],
        [
          1125.0,
          2658.0
        ],
        [
          1126.0,
          2706.0
        ],
        [
          681.0,
          2713.0
        ]
      ],
      "text": "произведение",
      "confidence": 0.9974631667137146
    },
    {
      "bbox": [
        [
          394.0,
          2792.0
        ],
        [
          580.0,
          2792.0
        ],
        [
          580.0,
          2854.0
        ],
        [
          394.0,
          2854.0
        ]
      ],
      "text": "а2,т",
      "confidence": 0.7582547664642334
    },
    {
      "bbox": [
        [
          620.0,
          2789.0
        ],
        [
          823.0,
          2789.0
        ],
        [
          823.0,
          2847.0
        ],
        [
          620.0,
          2847.0
        ]
      ],
      "text": "O,l-",
      "confidence": 0.7888827323913574
    },
    {
      "bbox": [
        [
          806.0,
          2789.0
        ],
        [
          1052.0,
          2789.0
        ],
        [
          1052.0,
          2847.0
        ],
        [
          806.0,
          2847.0
        ]
      ],
      "text": "2,7:10",
      "confidence": 0.8257203102111816
    },
    {
      "bbox": [
        [
          398.0,
          2909.0
        ],
        [
          458.0,
          2909.0
        ],
        [
          458.0,
          2967.0
        ],
        [
          398.0,
          2967.0
        ]
      ],
      "text": "б",
      "confidence": 0.996731162071228
    },
    {
      "bbox": [
        [
          469.0,
          2912.0
        ],
        [
          580.0,
          2912.0
        ],
        [
          580.0,
          2971.0
        ],
        [
          469.0,
          2971.0
        ]
      ],
      "text": "6,2",
      "confidence": 0.8256979584693909
    },
    {
      "bbox": [
        [
          620.0,
          2905.0
        ],
        [
          762.0,
          2905.0
        ],
        [
          762.0,
          2967.0
        ],
        [
          620.0,
          2967.0
        ]
      ],
      "text": "O,O",
      "confidence": 0.8174009323120117
    },
    {
      "bbox": [
        [
          846.0,
          2905.0
        ],
        [
          967.0,
          2905.0
        ],
        [
          967.0,
          2967.0
        ],
        [
          846.0,
          2967.0
        ]
      ],
      "text": "6,2",
      "confidence": 0.874934196472168
    },
    {
      "bbox": [
        [
          947.0,
          2916.0
        ],
        [
          998.0,
          2916.0
        ],
        [
          998.0,
          2957.0
        ],
        [
          947.0,
          2957.0
        ]
      ],
      "text": "?",
      "confidence": 0.5327829718589783
    },
    {
      "bbox": [
        [
          1001.0,
          2909.0
        ],
        [
          1123.0,
          2909.0
        ],
        [
          1123.0,
          2960.0
        ],
        [
          1001.0,
          2960.0
        ]
      ],
      "text": "оо",
      "confidence": 0.9774144887924194
    }
  ],
  "dimensions": {
    "width": 595.275634765625,
    "height": 791.1255493164062
  }
}